mr_kot/__init__.py
mr_kot/cli.py
mr_kot/decorators.py
mr_kot/param_spec.py
mr_kot/plugins.py
mr_kot/registry.py
mr_kot/runner.py
mr_kot/selectors.py
mr_kot/status.py
mr_kot/validators.py
mr_kot-0.8.5.dist-info/LICENSE
mr_kot-0.8.5.dist-info/METADATA
mr_kot-0.8.5.dist-info/WHEEL
mr_kot-0.8.5.dist-info/entry_points.txt
mr_kot-0.8.5.dist-info/RECORD
